splitme_ai/__init__.py
splitme_ai/cli.py
splitme_ai/config.py
splitme_ai/core.py
splitme_ai/errors.py
splitme_ai/logger.py
splitme_ai/generators/__init__.py
splitme_ai/generators/mkdocs_config.py
splitme_ai/tools/__init__.py
splitme_ai/tools/markdown_link_converter.py
splitme_ai/tools/markdown_link_validator.py
splitme_ai/tools/reference_link_extractor.py
splitme_ai/utils/__init__.py
splitme_ai/utils/file_handler.py
splitme_ai/utils/filename_sanitizer.py
splitme_ai-0.1.10.dist-info/METADATA
splitme_ai-0.1.10.dist-info/WHEEL
splitme_ai-0.1.10.dist-info/entry_points.txt
splitme_ai-0.1.10.dist-info/licenses/LICENSE
splitme_ai-0.1.10.dist-info/RECORD
